zero/__init__.py
zero/_stream.py
zero/_utils.py
zero/data.py
zero/hardware.py
zero/nn.py
zero/random.py
zero/tests/__init__.py
zero/tests/test__utils.py
zero/tests/test_data.py
zero/tests/test_hardware.py
zero/tests/test_nn.py
zero/tests/test_random.py
zero/tests/test_stream.py
zero/tests/util.py
libzero-0.0.8.dist-info/LICENSE
libzero-0.0.8.dist-info/WHEEL
libzero-0.0.8.dist-info/METADATA
libzero-0.0.8.dist-info/RECORD
