Metadata-Version: 2.1
Name: libzero
Version: 0.0.8
Summary: A zero-overhead library for PyTorch users.
Keywords: artificial intelligence,deep learning,library,python,pytorch,torch
Author-email: Yura52 <strausmg@gmail.com>
Requires-Python: >=3.7
Classifier: Intended Audience :: Developers
Classifier: Intended Audience :: Science/Research
Classifier: License :: OSI Approved :: MIT License
Classifier: Operating System :: MacOS
Classifier: Operating System :: Unix
Classifier: Programming Language :: Python :: 3
Classifier: Topic :: Scientific/Engineering :: Artificial Intelligence
Classifier: Topic :: Software Development :: Libraries :: Python Modules
Requires-Dist: numpy >=1.18,<2
Requires-Dist: pynvml >=11.0,<12
Requires-Dist: torch >=1.7,<2
Requires-Dist: tqdm >=4.0,<5
Project-URL: Code, https://github.com/Yura52/zero
Project-URL: Documentation, https://yura52.github.io/zero
